odoo/addons/ssi_product_line_mixin/README.rst
odoo/addons/ssi_product_line_mixin/__init__.py
odoo/addons/ssi_product_line_mixin/__manifest__.py
odoo/addons/ssi_product_line_mixin/menu.xml
odoo/addons/ssi_product_line_mixin/models/__init__.py
odoo/addons/ssi_product_line_mixin/models/mixin_product_line.py
odoo/addons/ssi_product_line_mixin/static/description/icon.png
odoo/addons/ssi_product_line_mixin/views/mixin_product_line_mixin_views.xml
odoo14_addon_ssi_product_line_mixin-14.0.1.3.0.dist-info/METADATA
odoo14_addon_ssi_product_line_mixin-14.0.1.3.0.dist-info/WHEEL
odoo14_addon_ssi_product_line_mixin-14.0.1.3.0.dist-info/top_level.txt
odoo14_addon_ssi_product_line_mixin-14.0.1.3.0.dist-info/RECORD
